benji/__init__.py
benji/_static_version.py
benji/_version.py
benji/aes_keywrap.py
benji/benji.py
benji/blockuidhistory.py
benji/commands.py
benji/config.py
benji/database.py
benji/exception.py
benji/jobexecutor.py
benji/logging.py
benji/nbdserver.py
benji/repr.py
benji/restapi.py
benji/retentionfilter.py
benji/utils.py
benji/versions.py
benji/helpers/__init__.py
benji/helpers/ceph.py
benji/helpers/prometheus.py
benji/helpers/restapi.py
benji/helpers/settings.py
benji/helpers/utils.py
benji/io/__init__.py
benji/io/base.py
benji/io/factory.py
benji/io/file.py
benji/io/iscsi.py
benji/io/rbd.py
benji/io/rbdaio.py
benji/schemas/v1/benji.config.yaml
benji/schemas/v1/benji.io.file.yaml
benji/schemas/v1/benji.io.iscsi.yaml
benji/schemas/v1/benji.io.rbd.yaml
benji/schemas/v1/benji.io.rbdaio.yaml
benji/schemas/v1/benji.storage.b2.yaml
benji/schemas/v1/benji.storage.base.ReadCache.yaml
benji/schemas/v1/benji.storage.base.yaml
benji/schemas/v1/benji.storage.file.yaml
benji/schemas/v1/benji.storage.s3.yaml
benji/schemas/v1/benji.transform.aes_256_gcm.yaml
benji/schemas/v1/benji.transform.aes_256_gcm_ecc.yaml
benji/schemas/v1/benji.transform.base.yaml
benji/schemas/v1/benji.transform.zstd.yaml
benji/scripts/__init__.py
benji/scripts/benji.py
benji/sql_migrations/__init__.py
benji/sql_migrations/alembic.ini
benji/sql_migrations/alembic/__init__.py
benji/sql_migrations/alembic/env.py
benji/sql_migrations/alembic/versions/013dd9461e2c_rename_snapshot_name_to_snapshot_in_.py
benji/sql_migrations/alembic/versions/151248f94062_remove_stats_table.py
benji/sql_migrations/alembic/versions/2bb97229fe36_rename_id_to_idx_in_table_blocks.py
benji/sql_migrations/alembic/versions/2e028f08346b_update_20190118_1.py
benji/sql_migrations/alembic/versions/368014edd88c_fix_blocks_primary_key.py
benji/sql_migrations/alembic/versions/3d014d45493f_bytes_dedup.py
benji/sql_migrations/alembic/versions/__init__.py
benji/sql_migrations/alembic/versions/b1fa564a0ebf_add_version_status.py
benji-0.17.0.dist-info/LICENSE.txt
benji-0.17.0.dist-info/METADATA
benji-0.17.0.dist-info/WHEEL
benji-0.17.0.dist-info/entry_points.txt
benji-0.17.0.dist-info/top_level.txt
benji-0.17.0.dist-info/RECORD
