Metadata-Version: 2.1
Name: benji
Version: 0.17.0
Summary: A block based deduplicating backup software for Ceph RBD, image files and devices 
Home-page: https://benji-backup.me/
Author: Lars Fenneberg <lf@elemental.net>, Daniel Kraft <daniel.kraft@d9t.de>
Author-email: lf@elemental.net, daniel.kraft@d9t.de
License: LGPL-3
Keywords: backup
Classifier: Development Status :: 3 - Alpha
Classifier: Environment :: Console
Classifier: Intended Audience :: System Administrators
Classifier: License :: OSI Approved :: GNU Lesser General Public License v3 (LGPLv3)
Classifier: Operating System :: POSIX
Classifier: Programming Language :: Python :: 3.6
Classifier: Programming Language :: Python :: 3.7
Classifier: Programming Language :: Python :: 3.8
Classifier: Programming Language :: Python :: 3.9
Classifier: Topic :: System :: Archiving :: Backup
Requires-Python: ~=3.6
License-File: LICENSE.txt
Requires-Dist: PrettyTable (<1,>=0.7.2)
Requires-Dist: sqlalchemy (<2,>=1.4.14)
Requires-Dist: setproctitle (<2,>=1.1.8)
Requires-Dist: python-dateutil (<3,>=2.6.0)
Requires-Dist: alembic (<2,>=1.0.5)
Requires-Dist: ruamel.yaml (<0.16,>0.15)
Requires-Dist: psycopg2-binary (<3,>=2.7.4)
Requires-Dist: argcomplete (<2,>=1.9.4)
Requires-Dist: sparsebitfield (<1,>=0.2.3)
Requires-Dist: cerberus (<2,>=1.2)
Requires-Dist: pycryptodome (<4,>=3.6.1)
Requires-Dist: pyparsing (<3,>=2.3.0)
Requires-Dist: semantic-version (<3,>=2.8.1)
Requires-Dist: dateparser (<2,>=1.1.1)
Requires-Dist: structlog (>=19.1.0)
Requires-Dist: colorama (<1,>=0.4.1)
Requires-Dist: diskcache (>=3.0.6)
Requires-Dist: attrs (<22,>=21.4.0)
Provides-Extra: b2
Requires-Dist: b2sdk (<2,>=1.4.0) ; extra == 'b2'
Provides-Extra: compression
Requires-Dist: zstandard (>=0.9.0) ; extra == 'compression'
Provides-Extra: dev
Requires-Dist: parameterized ; extra == 'dev'
Requires-Dist: wheel ; extra == 'dev'
Requires-Dist: yapf ; extra == 'dev'
Requires-Dist: mypy ; extra == 'dev'
Requires-Dist: pytest ; extra == 'dev'
Requires-Dist: build ; extra == 'dev'
Provides-Extra: doc
Requires-Dist: sphinx ; extra == 'doc'
Requires-Dist: sphinx-rtd-theme ; extra == 'doc'
Requires-Dist: sphinxcontrib-programoutput ; extra == 'doc'
Provides-Extra: helpers
Requires-Dist: blinker (<2,>=1.4) ; extra == 'helpers'
Requires-Dist: prometheus-client (<1,>=0.7.0) ; extra == 'helpers'
Provides-Extra: rest-api
Requires-Dist: bottle (<0.13.0,>=0.12.16) ; extra == 'rest-api'
Requires-Dist: gunicorn (<20,>=19.9.0) ; extra == 'rest-api'
Requires-Dist: webargs (<6,>=5.3.1) ; extra == 'rest-api'
Requires-Dist: requests (<3,>=2.22.0) ; extra == 'rest-api'
Provides-Extra: s3
Requires-Dist: boto3 (>=1.15.0) ; extra == 's3'
